<annotation>
	<folder>images</folder>
	<filename>000428.jpg</filename>
	<path>/Users/radualbastroiu/Documents/My_Projects/Licenta/ML-Object-Recognition/data/CarImagesLabeled/images/000428.jpg</path>
	<source>
		<database>Unknown</database>
	</source>
	<size>
		<width>730</width>
		<height>411</height>
		<depth>3</depth>
	</size>
	<segmented>0</segmented>
	<object>
		<name>Car</name>
		<pose>Unspecified</pose>
		<truncated>0</truncated>
		<difficult>0</difficult>
		<bndbox>
			<xmin>80</xmin>
			<ymin>72</ymin>
			<xmax>636</xmax>
			<ymax>316</ymax>
		</bndbox>
	</object>
</annotation>
